waylay/services/queries/models/__init__.py
waylay/services/queries/models/aggregation_by_resource_and_metric_value.py
waylay/services/queries/models/aggregation_by_resource_or_metric_value.py
waylay/services/queries/models/aggregation_method.py
waylay/services/queries/models/aggregation_method_one_of.py
waylay/services/queries/models/aggregation_method_one_of1.py
waylay/services/queries/models/aggregation_method_one_of2.py
waylay/services/queries/models/aggregation_method_one_of3.py
waylay/services/queries/models/aggregation_method_one_of4.py
waylay/services/queries/models/aggregation_method_one_of5.py
waylay/services/queries/models/aggregation_method_one_of6.py
waylay/services/queries/models/aggregation_method_one_of7.py
waylay/services/queries/models/aggregation_method_one_of8.py
waylay/services/queries/models/aggregations_inner.py
waylay/services/queries/models/align_at.py
waylay/services/queries/models/align_shift.py
waylay/services/queries/models/alignment.py
waylay/services/queries/models/alignment_grid_interval.py
waylay/services/queries/models/alignment_timezone.py
waylay/services/queries/models/cause_exception.py
waylay/services/queries/models/column_data_set.py
waylay/services/queries/models/column_data_set_data_axis.py
waylay/services/queries/models/column_header.py
waylay/services/queries/models/column_headers_inner.py
waylay/services/queries/models/data.py
waylay/services/queries/models/data_axis_option.py
waylay/services/queries/models/data_set_attributes.py
waylay/services/queries/models/data_set_window.py
waylay/services/queries/models/datum.py
waylay/services/queries/models/default_aggregation.py
waylay/services/queries/models/default_interpolation.py
waylay/services/queries/models/delete_response.py
waylay/services/queries/models/embeddings_value.py
waylay/services/queries/models/from_override.py
waylay/services/queries/models/grouping_interval.py
waylay/services/queries/models/grouping_interval_override.py
waylay_sdk_queries_types-0.5.0.20241025.dist-info/LICENSE.txt
waylay_sdk_queries_types-0.5.0.20241025.dist-info/METADATA
waylay_sdk_queries_types-0.5.0.20241025.dist-info/WHEEL
waylay_sdk_queries_types-0.5.0.20241025.dist-info/top_level.txt
waylay_sdk_queries_types-0.5.0.20241025.dist-info/RECORD
